README.rst
setup.py
minicss/__init__.py
minicss/cli.py
minicss.egg-info/PKG-INFO
minicss.egg-info/SOURCES.txt
minicss.egg-info/dependency_links.txt
minicss.egg-info/entry_points.txt
minicss.egg-info/not-zip-safe
minicss.egg-info/requires.txt
minicss.egg-info/top_level.txt