Metadata-Version: 1.1
Name: minicss
Version: 1.2
Summary: # MINI CSS
